palign/VERSION
palign/__init__.py
palign/py.typed
palign-0.0.0.dist-info/LICENSE
palign-0.0.0.dist-info/METADATA
palign-0.0.0.dist-info/WHEEL
palign-0.0.0.dist-info/top_level.txt
palign-0.0.0.dist-info/RECORD
