Metadata-Version: 2.1
Name: palign
Version: 0.0.0
Summary: Pillow text alignment helper
Home-page: https://github.com/cariad/palign
Author: Cariad Eccleston
Author-email: cariad@cariad.earth
License: MIT
Classifier: Development Status :: 5 - Production/Stable
Classifier: License :: OSI Approved :: MIT License
Classifier: Natural Language :: English
Classifier: Operating System :: OS Independent
Classifier: Programming Language :: Python :: 3 :: Only
Classifier: Programming Language :: Python :: 3.10
Classifier: Programming Language :: Python :: 3.11
Classifier: Programming Language :: Python :: 3.9
Classifier: Typing :: Typed
Requires-Python: >=3.9
License-File: LICENSE
